django_db_seed/__init__.py
django_db_seed/admin.py
django_db_seed/apps.py
django_db_seed/helpers.py
django_db_seed/models.py
django_db_seed/tests.py
django_db_seed/urls.py
django_db_seed/views.py
django_db_seed/management/commands/db-seed.py
django_db_seed/migrations/__init__.py
django_db_seed-1.0.1.dist-info/LICENSE.md
django_db_seed-1.0.1.dist-info/METADATA
django_db_seed-1.0.1.dist-info/WHEEL
django_db_seed-1.0.1.dist-info/top_level.txt
django_db_seed-1.0.1.dist-info/RECORD
