Metadata-Version: 2.1
Name: django-db-seed
Version: 1.0.1
Summary: A Django app to backup and restore the database.
Home-page: https://github.com/AfzalSabbir/django_db_seed
Author: Afzalur Rahman Sabbir
Author-email: afzalbd1@gmail.com
License: MIT
Classifier: Environment :: Web Environment
Classifier: Framework :: Django
Classifier: Framework :: Django :: 5.0
Classifier: Intended Audience :: Developers
Classifier: License :: OSI Approved :: MIT License
Classifier: Operating System :: OS Independent
Classifier: Programming Language :: Python
Classifier: Programming Language :: Python :: 3
Classifier: Programming Language :: Python :: 3.12
Classifier: Topic :: Internet :: WWW/HTTP
Classifier: Topic :: Internet :: WWW/HTTP :: Dynamic Content
Requires-Python: >=3.10
License-File: LICENSE.md
Requires-Dist: Django >=5.0.3
